classic_ID3_decision_tree/__init__.py
classic_ID3_DecisionTree-2.0.3.dist-info/LICENSE
classic_ID3_DecisionTree-2.0.3.dist-info/METADATA
classic_ID3_DecisionTree-2.0.3.dist-info/WHEEL
classic_ID3_DecisionTree-2.0.3.dist-info/top_level.txt
classic_ID3_DecisionTree-2.0.3.dist-info/RECORD
